README.md
setup.cfg
setup.py
financekit/__init__.py
financekit/liquidity_ratios.py
financekit.egg-info/PKG-INFO
financekit.egg-info/SOURCES.txt
financekit.egg-info/dependency_links.txt
financekit.egg-info/top_level.txt